healthy_api/__init__.py
healthy_api/git.py
healthy_api/version.py
healthy_api/adapters/base_adapter.py
healthy_api/adapters/fastapi.py
healthy_api/adapters/flask.py
Healthy_API-0.9.0.dist-info/AUTHORS.rst
Healthy_API-0.9.0.dist-info/LICENSE
Healthy_API-0.9.0.dist-info/METADATA
Healthy_API-0.9.0.dist-info/WHEEL
Healthy_API-0.9.0.dist-info/top_level.txt
Healthy_API-0.9.0.dist-info/RECORD
